<?xml version="1.0" encoding="UTF-8"?>
<objects serializationModel="Studio.02.00.00">
	<object class="AudioFile" id="{a16aa7a2-85ad-4d56-9931-b57c576f4b02}">
		<property name="assetPath">
			<value>Bullet, Impact, Body, Thump 8 SND6353.wav</value>
		</property>
		<property name="frequencyInKHz">
			<value>96</value>
		</property>
		<property name="channelCount">
			<value>2</value>
		</property>
		<property name="length">
			<value>0.080302083333333329</value>
		</property>
		<relationship name="masterAssetFolder">
			<destination>{f51859a2-5901-4603-befc-9dff2de62263}</destination>
		</relationship>
	</object>
</objects>
