<?xml version="1.0" encoding="UTF-8"?>
<objects serializationModel="Studio.02.00.00">
	<object class="AudioFile" id="{bcbfea02-9812-40b7-be9e-2e21233df364}">
		<property name="assetPath">
			<value>Human, Vocal, Male, Grunt, Grumble, Caveman 3 SND23726.wav</value>
		</property>
		<property name="frequencyInKHz">
			<value>96</value>
		</property>
		<property name="channelCount">
			<value>2</value>
		</property>
		<property name="length">
			<value>0.40777083333333336</value>
		</property>
		<relationship name="masterAssetFolder">
			<destination>{f51859a2-5901-4603-befc-9dff2de62263}</destination>
		</relationship>
	</object>
</objects>
